npc/vsrc/example.v
module example(
  input        a,
  input        b,
  output       y
);

assign y = a ^ b;

endmodule

module top_example (
  input       clk,
  input       rst,
  input        a,
  input        b,
  output       y
);

  example u_example (
    .a(a),
    .b(b),
    .y(y)
);
  
endmodule

npc/waveform.vcd
$version Generated by VerilatedVcd $end
$timescale 1ps $end
 $scope module TOP $end
  $var wire 1 # clk $end
  $var wire 1 $ rst $end
  $var wire 1 % a $end
  $var wire 1 & b $end
  $var wire 1 ' y $end
  $scope module top_example $end
   $var wire 1 # clk $end
   $var wire 1 $ rst $end
   $var wire 1 % a $end
   $var wire 1 & b $end
   $var wire 1 ' y $end
   $scope module u_example $end
    $var wire 1 % a $end
    $var wire 1 & b $end
    $var wire 1 ' y $end
   $upscope $end
  $upscope $end
 $upscope $end
$enddefinitions $end


#0
0#
0$
0%
0&
0'
#1
1#
1$
#2
0#
1%
1'
#3
1#
#4
0#
1&
0'
#5
1#
#6
0#
#7
1#
#8
0#
0%
0&
#9
1#
#10
0#
1%
1&
#11
1#
#12
0#
0%
1'
#13
1#
#14
0#
#15
1#
#16
0#
1%
0&
#17
1#
#18
0#
0%
0'
#19
1#
#20
0#
#21
1#
#22
0#
1%
1'
#23
1#
#24
0#
1&
0'
#25
1#
#26
0#
0%
0&
#27
1#
#28
0#
1&
1'
#29
1#
#30
0#
1%
0'
#31
1#
#32
0#
0&
1'
#33
1#
#34
0#
0%
0'
#35
1#
#36
0#
1%
1&
#37
1#
#38
0#
0&
1'
#39
1#
#40
0#
#41
1#
#42
0#
1&
0'
#43
1#
#44
0#
#45
1#
#46
0#
0%
1'
#47
1#
#48
0#
0&
0'
#49
1#
#50
0#
1%
1'
#51
1#
#52
0#
#53
1#
#54
0#
#55
1#
#56
0#
0%
1&
#57
1#
#58
0#
0&
0'
#59
1#
#60
0#
1&
1'
#61
1#
#62
0#
1%
0'
#63
1#
#64
0#
0%
1'
#65
1#
#66
0#
#67
1#
#68
0#
#69
1#
#70
0#
1%
0'
#71
1#
#72
0#
0%
1'
#73
1#
#74
0#
#75
1#
#76
0#
#77
1#
#78
0#
0&
0'
#79
1#
#80
0#
1%
1'
#81
1#
#82
0#
#83
1#
#84
0#
0%
0'
#85
1#
#86
0#
#87
1#
#88
0#
1%
1&
#89
1#
#90
0#
0%
1'
#91
1#
#92
0#
0&
0'
#93
1#
#94
0#
#95
1#
#96
0#
1%
1'
#97
1#
#98
0#
0%
0'
#99
1#
#100
0#
1&
1'
#101
1#
#102
0#
1%
0&
#103
1#
#104
0#
0%
0'
#105
1#
#106
0#
1%
1&
#107
1#
#108
0#
0&
1'
#109
1#
#110
0#
#111
1#
#112
0#
0%
0'
#113
1#
#114
0#
1%
1'
#115
1#
#116
0#
0%
1&
#117
1#
#118
0#
1%
0'
#119
1#
#120
0#
0%
1'
#121
1#
#122
0#
#123
1#
#124
0#
1%
0'
#125
1#
#126
0#
#127
1#
#128
0#
#129
1#
#130
0#
#131
1#
#132
0#
0&
1'
#133
1#
#134
0#
1&
0'
#135
1#
#136
0#
0%
1'
#137
1#
#138
0#
#139
1#
#140
0#
1%
0&
#141
1#
#142
0#
0%
1&
#143
1#
#144
0#
#145
1#
#146
0#
1%
0'
#147
1#
#148
0#
0%
0&
#149
1#
#150
0#
1&
1'
#151
1#
#152
0#
#153
1#
#154
0#
#155
1#
#156
0#
#157
1#
#158
0#
#159
1#
#160
0#
1%
0'
#161
1#
#162
0#
0&
1'
#163
1#
#164
0#
0%
0'
#165
1#
#166
0#
1%
1'
#167
1#
#168
0#
#169
1#
#170
0#
0%
0'
#171
1#
#172
0#
#173
1#
#174
0#
1%
1'
#175
1#
#176
0#
1&
0'
#177
1#
#178
0#
#179
1#
#180
0#
0&
1'
#181
1#
#182
0#
0%
1&
#183
1#
#184
0#
1%
0&
#185
1#
#186
0#
1&
0'
#187
1#
#188
0#
0%
1'
#189
1#
#190
0#
#191
1#
#192
0#
1%
0'
#193
1#
#194
0#
#195
1#
#196
0#
0%
0&
#197
1#
#198
0#
1%
1&
#199
1#
#200
0#
0%
1'
#201
1#
#202
0#
0&
0'
#203
1#
#204
0#
1%
1&
#205
1#
#206
0#
0&
1'
#207
1#
#208
0#
0%
0'
#209
1#
#210
0#
#211
1#
#212
0#
#213
1#
#214
0#
1%
1&
#215
1#
#216
0#
0&
1'
#217
1#
#218
0#
0%
1&
#219
1#
#220
0#
#221
1#
#222
0#
#223
1#
#224
0#
#225
1#
#226
0#
0&
0'
#227
1#
#228
0#
1%
1&
#229
1#
#230
0#
0%
0&
#231
1#
#232
0#
1%
1'
#233
1#
#234
0#
0%
0'
#235
1#
#236
0#
1%
1&
#237
1#
#238
0#
0&
1'
#239
1#
#240
0#
0%
1&
#241
1#
#242
0#
0&
0'
#243
1#
#244
0#
1%
1&
#245
1#
#246
0#
0%
0&
#247
1#
#248
0#
#249
1#
#250
0#
1%
1'
#251
1#
#252
0#
1&
0'
#253
1#
#254
0#
0&
1'
#255
1#
#256
0#
0%
1&
#257
1#
#258
0#
0&
0'
#259
1#
#260
0#
#261
1#
#262
0#
1&
1'
#263
1#
#264
0#
0&
0'
#265
1#
#266
0#
#267
1#
#268
0#
1&
1'
#269
1#
#270
0#
0&
0'
#271
1#
#272
0#
#273
1#
#274
0#
1&
1'
#275
1#
#276
0#
1%
0&
#277
1#
#278
0#
0%
1&
#279
1#
#280
0#
1%
0'
#281
1#
#282
0#
0&
1'
#283
1#
#284
0#
#285
1#
#286
0#
0%
1&
#287
1#
#288
0#
1%
0'
#289
1#
#290
0#
0&
1'
#291
1#
#292
0#
1&
0'
#293
1#
#294
0#
0&
1'
#295
1#
#296
0#
0%
1&
#297
1#
#298
0#
0&
0'
#299
1#
#300
0#
#301
1#
#302
0#
#303
1#
#304
0#
#305
1#
#306
0#
1&
1'
#307
1#
#308
0#
1%
0&
#309
1#
#310
0#
#311
1#
#312
0#
#313
1#
#314
0#
0%
0'
#315
1#
#316
0#
1%
1&
#317
1#
#318
0#
0%
0&
#319
1#
#320
0#
1&
1'
#321
1#
#322
0#
#323
1#
#324
0#
1%
0&
#325
1#
#326
0#
1&
0'
#327
1#
#328
0#
#329
1#
#330
0#
0&
1'
#331
1#
#332
0#
1&
0'
#333
1#
#334
0#
0%
1'
#335
1#
#336
0#
1%
0&
#337
1#
#338
0#
#339
1#
#340
0#
0%
0'
#341
1#
#342
0#
#343
1#
#344
0#
1&
1'
#345
1#
#346
0#
#347
1#
#348
0#
0&
0'
#349
1#
#350
0#
#351
1#
#352
0#
#353
1#
#354
0#
1%
1&
#355
1#
#356
0#
0%
1'
#357
1#
#358
0#
0&
0'
#359
1#
#360
0#
1&
1'
#361
1#
#362
0#
0&
0'
#363
1#
#364
0#
#365
1#
#366
0#
1%
1&
#367
1#
#368
0#
0&
1'
#369
1#
#370
0#
0%
1&
#371
1#
#372
0#
0&
0'
#373
1#
#374
0#
1%
1&
#375
1#
#376
0#
0&
1'
#377
1#
#378
0#
0%
1&
#379
1#
#380
0#
0&
0'
#381
1#
#382
0#
1%
1'
#383
1#
#384
0#
1&
0'
#385
1#
#386
0#
#387
1#
#388
0#
0%
1'
#389
1#
#390
0#
1%
0&
#391
1#
#392
0#
0%
1&
#393
1#
#394
0#
0&
0'
#395
1#
#396
0#
#397
1#
#398
0#
1&
1'
#399
1#
#400
0#
0&
0'
#401
1#
#402
0#
1&
1'
#403
1#
#404
0#
0&
0'
#405
1#
#406
0#
#407
1#
#408
0#
#409
1#
#410
0#
1%
1'
#411
1#
#412
0#
1&
0'
#413
1#
#414
0#
0&
1'
#415
1#
#416
0#
0%
0'
#417
1#
#418
0#
1%
1'
#419
1#
#420
0#
0%
1&
#421
1#
#422
0#
0&
0'
#423
1#
#424
0#
1&
1'
#425
1#
#426
0#
1%
0&
#427
1#
#428
0#
1&
0'
#429
1#
#430
0#
#431
1#
#432
0#
0&
1'
#433
1#
#434
0#
0%
1&
#435
1#
#436
0#
0&
0'
#437
1#
#438
0#
1%
1'
#439
1#
#440
0#
1&
0'
#441
1#
#442
0#
0%
0&
#443
1#
#444
0#
1&
1'
#445
1#
#446
0#
0&
0'
#447
1#
#448
0#
1&
1'
#449
1#
#450
0#
0&
0'
#451
1#
#452
0#
#453
1#
#454
0#
1&
1'
#455
1#
#456
0#
1%
0'
#457
1#
#458
0#
0&
1'
#459
1#
#460
0#
0%
1&
#461
1#
#462
0#
#463
1#
#464
0#
1%
0&
#465
1#
#466
0#
1&
0'
#467
1#
#468
0#
0&
1'
#469
1#
#470
0#
#471
1#
#472
0#
1&
0'
#473
1#
#474
0#
0%
1'
#475
1#
#476
0#
1%
0&
#477
1#
#478
0#
1&
0'
#479
1#
#480
0#
#481
1#
#482
0#
0&
1'
#483
1#
#484
0#
0%
1&
#485
1#
#486
0#
1%
0'
#487
1#
#488
0#
0&
1'
#489
1#
#490
0#
0%
1&
#491
1#
#492
0#
1%
0&
#493
1#
#494
0#
#495
1#
#496
0#
0%
0'
#497
1#
#498
0#
1%
1&
#499
1#
#500
0#
0%
0&
#501
1#
#502
0#
1%
1'
#503
1#
#504
0#
0%
1&
#505
1#
#506
0#
1%
0'
#507
1#
#508
0#
#509
1#
#510
0#
0%
1'
#511
1#
#512
0#
#513
1#
#514
0#
1%
0&
#515
1#
#516
0#
0%
0'
#517
1#
#518
0#
1&
1'
#519
1#
#520
0#
0&
0'
#521
1#
#522
0#
1%
1'
#523
1#
#524
0#
0%
0'
#525
1#
#526
0#
#527
1#
#528
0#
#529
1#
#530
0#
#531
1#
#532
0#
1&
1'
#533
1#
#534
0#
0&
0'
#535
1#
#536
0#
1%
1'
#537
1#
#538
0#
#539
1#
#540
0#
1&
0'
#541
1#
#542
0#
#543
1#
#544
0#
0%
0&
#545
1#
#546
0#
1&
1'
#547
1#
#548
0#
0&
0'
#549
1#
#550
0#
1&
1'
#551
1#
#552
0#
#553
1#
#554
0#
1%
0&
#555
1#
#556
0#
1&
0'
#557
1#
#558
0#
0%
1'
#559
1#
#560
0#
1%
0&
#561
1#
#562
0#
0%
0'
#563
1#
#564
0#
#565
1#
#566
0#
1&
1'
#567
1#
#568
0#
0&
0'
#569
1#
#570
0#
1%
1&
#571
1#
#572
0#
#573
1#
#574
0#
0&
1'
#575
1#
#576
0#
1&
0'
#577
1#
#578
0#
0&
1'
#579
1#
#580
0#
1&
0'
#581
1#
#582
0#
#583
1#
#584
0#
0&
1'
#585
1#
#586
0#
#587
1#
#588
0#
1&
0'
#589
1#
#590
0#
0%
1'
#591
1#
#592
0#
0&
0'
#593
1#
#594
0#
1%
1'
#595
1#
#596
0#
0%
1&
#597
1#
#598
0#
1%
0'
#599
1#
#600
0#
0&
1'
#601
1#
#602
0#
0%
1&
#603
1#
#604
0#
1%
0'
#605
1#
#606
0#
#607
1#
#608
0#
0%
0&
#609
1#
#610
0#
1%
1&
#611
1#
#612
0#
0&
1'
#613
1#
#614
0#
0%
0'
#615
1#
#616
0#
1&
1'
#617
1#
#618
0#
1%
0'
#619
1#
#620
0#
#621
1#
#622
0#
0%
1'
#623
1#
#624
0#
1%
0'
#625
1#
#626
0#
#627
1#
#628
0#
0&
1'
#629
1#
#630
0#
0%
0'
#631
1#
#632
0#
1&
1'
#633
1#
#634
0#
1%
0&
#635
1#
#636
0#
0%
0'
#637
1#
#638
0#
1%
1&
#639
1#
#640
0#
0%
0&
#641
1#
#642
0#
#643
1#
#644
0#
1&
1'
#645
1#
#646
0#
0&
0'
#647
1#
#648
0#
1&
1'
#649
1#
#650
0#
1%
0'
#651
1#
#652
0#
0%
0&
#653
1#
#654
0#
1&
1'
#655
1#
#656
0#
1%
0'
#657
1#
#658
0#
0&
1'
#659
1#
#660
0#
1&
0'
#661
1#
#662
0#
0&
1'
#663
1#
#664
0#
0%
0'
#665
1#
#666
0#
1&
1'
#667
1#
#668
0#
1%
0'
#669
1#
#670
0#
0%
1'
#671
1#
#672
0#
1%
0&
#673
1#
#674
0#
1&
0'
#675
1#
#676
0#
0&
1'
#677
1#
#678
0#
#679
1#
#680
0#
#681
1#
#682
0#
#683
1#
#684
0#
0%
0'
#685
1#
#686
0#
1%
1'
#687
1#
#688
0#
#689
1#
#690
0#
0%
1&
#691
1#
#692
0#
#693
1#
#694
0#
1%
0&
#695
1#
#696
0#
0%
1&
#697
1#
#698
0#
1%
0'
#699
1#
#700
0#
0%
1'
#701
1#
#702
0#
#703
1#
#704
0#
0&
0'
#705
1#
#706
0#
1&
1'
#707
1#
#708
0#
#709
1#
#710
0#
1%
0'
#711
1#
#712
0#
#713
1#
#714
0#
0&
1'
#715
1#
#716
0#
1&
0'
#717
1#
#718
0#
0%
0&
#719
1#
#720
0#
1%
1'
#721
1#
#722
0#
1&
0'
#723
1#
#724
0#
0%
0&
#725
1#
#726
0#
#727
1#
#728
0#
1%
1&
#729
1#
#730
0#
#731
1#
#732
0#
#733
1#
#734
0#
0%
1'
#735
1#
#736
0#
1%
0&
#737
1#
#738
0#
0%
1&
#739
1#
#740
0#
1%
0&
#741
1#
#742
0#
1&
0'
#743
1#
#744
0#
0&
1'
#745
1#
#746
0#
#747
1#
#748
0#
1&
0'
#749
1#
#750
0#
0%
1'
#751
1#
#752
0#
1%
0&
#753
1#
#754
0#
0%
1&
#755
1#
#756
0#
0&
0'
#757
1#
#758
0#
1%
1'
#759
1#
#760
0#
0%
0'
#761
1#
#762
0#
1%
1&
#763
1#
#764
0#
0%
0&
#765
1#
#766
0#
1&
1'
#767
1#
#768
0#
0&
0'
#769
1#
#770
0#
1%
1'
#771
1#
#772
0#
0%
0'
#773
1#
#774
0#
1%
1&
#775
1#
#776
0#
0%
0&
#777
1#
#778
0#
1%
1'
#779
1#
#780
0#
#781
1#
#782
0#
#783
1#
#784
0#
0%
1&
#785
1#
#786
0#
0&
0'
#787
1#
#788
0#
1&
1'
#789
1#
#790
0#
0&
0'
#791
1#
#792
0#
#793
1#
#794
0#
1%
1'
#795
1#
#796
0#
0%
1&
#797
1#
#798
0#
1%
0&
#799
1#
#800
0#
#801
1#
#802
0#
0%
0'
#803
1#
#804
0#
1&
1'
#805
1#
#806
0#
1%
0'
#807
1#
#808
0#
#809
1#
#810
0#
0&
1'
#811
1#
#812
0#
#813
1#
#814
0#
1&
0'
#815
1#
#816
0#
#817
1#
#818
0#
#819
1#
#820
0#
0%
0&
#821
1#
#822
0#
1%
1'
#823
1#
#824
0#
0%
0'
#825
1#
#826
0#
#827
1#
#828
0#
1%
1'
#829
1#
#830
0#
0%
1&
#831
1#
#832
0#
#833
1#
#834
0#
1%
0'
#835
1#
#836
0#
0%
0&
#837
1#
#838
0#
#839
1#
#840
0#
1%
1&
#841
1#
#842
0#
0%
0&
#843
1#
#844
0#
1%
1&
#845
1#
#846
0#
0&
1'
#847
1#
#848
0#
0%
1&
#849
1#
#850
0#
#851
1#
#852
0#
1%
0'
#853
1#
#854
0#
#855
1#
#856
0#
0%
0&
#857
1#
#858
0#
1%
1&
#859
1#
#860
0#
0%
1'
#861
1#
#862
0#
0&
0'
#863
1#
#864
0#
1&
1'
#865
1#
#866
0#
1%
0'
#867
1#
#868
0#
0%
1'
#869
1#
#870
0#
1%
0'
#871
1#
#872
0#
0%
1'
#873
1#
#874
0#
#875
1#
#876
0#
1%
0'
#877
1#
#878
0#
0%
1'
#879
1#
#880
0#
0&
0'
#881
1#
#882
0#
1&
1'
#883
1#
#884
0#
1%
0&
#885
1#
#886
0#
0%
1&
#887
1#
#888
0#
#889
1#
#890
0#
1%
0&
#891
1#
#892
0#
1&
0'
#893
1#
#894
0#
0%
1'
#895
1#
#896
0#
1%
0&
#897
1#
#898
0#
0%
1&
#899
1#
#900
0#
1%
0'
#901
1#
#902
0#
0%
0&
#903
1#
#904
0#
1%
1'
#905
1#
#906
0#
#907
1#
#908
0#
0%
1&
#909
1#
#910
0#
1%
0&
#911
1#
#912
0#
#913
1#
#914
0#
0%
1&
#915
1#
#916
0#
0&
0'
#917
1#
#918
0#
#919
1#
#920
0#
1&
1'
#921
1#
#922
0#
#923
1#
#924
0#
1%
0&
#925
1#
#926
0#
0%
0'
#927
1#
#928
0#
1&
1'
#929
1#
#930
0#
1%
0&
#931
1#
#932
0#
0%
1&
#933
1#
#934
0#
#935
1#
#936
0#
#937
1#
#938
0#
1%
0&
#939
1#
#940
0#
1&
0'
#941
1#
#942
0#
0%
0&
#943
1#
#944
0#
1%
1'
#945
1#
#946
0#
1&
0'
#947
1#
#948
0#
0&
1'
#949
1#
#950
0#
1&
0'
#951
1#
#952
0#
#953
1#
#954
0#
0%
0&
#955
1#
#956
0#
1%
1'
#957
1#
#958
0#
0%
0'
#959
1#
#960
0#
1%
1&
#961
1#
#962
0#
0%
0&
#963
1#
#964
0#
1%
1'
#965
1#
#966
0#
1&
0'
#967
1#
#968
0#
#969
1#
#970
0#
0&
1'
#971
1#
#972
0#
0%
1&
#973
1#
#974
0#
1%
0'
#975
1#
#976
0#
0%
0&
#977
1#
#978
0#
1&
1'
#979
1#
#980
0#
#981
1#
#982
0#
0&
0'
#983
1#
#984
0#
#985
1#
#986
0#
1&
1'
#987
1#
#988
0#
#989
1#
#990
0#
1%
0&
#991
1#
#992
0#
0%
1&
#993
1#
#994
0#
#995
1#
#996
0#
1%
0'
#997
1#
#998
0#
0%
1'
#999
1#
#1000
0#
#1001
1#
#1002
0#
1%
0&
#1003
1#
#1004
0#
#1005
1#
#1006
0#
1&
0'
#1007
1#
#1008
0#
#1009
1#
#1010
0#
0%
1'
#1011
1#
#1012
0#
0&
0'
#1013
1#
#1014
0#
1%
1'
#1015
1#
#1016
0#
0%
0'
#1017
1#
#1018
0#
#1019
1#
#1020
0#
1%
1&
#1021
1#
#1022
0#
0%
1'
#1023
1#
#1024
0#
1%
0&
#1025
1#
#1026
0#
#1027
1#
#1028
0#
0%
1&
#1029
1#
#1030
0#
1%
0&
#1031
1#
#1032
0#
1&
0'
#1033
1#
#1034
0#
0&
1'
#1035
1#
#1036
0#
#1037
1#
#1038
0#
#1039
1#
#1040
0#
0%
1&
#1041
1#
#1042
0#
0&
0'
#1043
1#
#1044
0#
1%
1&
#1045
1#
#1046
0#
#1047
1#
#1048
0#
#1049
1#
#1050
0#
0&
1'
#1051
1#
#1052
0#
0%
0'
#1053
1#
#1054
0#
1&
1'
#1055
1#
#1056
0#
#1057
1#
#1058
0#
0&
0'
#1059
1#
#1060
0#
1&
1'
#1061
1#
#1062
0#
1%
0'
#1063
1#
#1064
0#
0%
0&
#1065
1#
#1066
0#
1%
1'
#1067
1#
#1068
0#
0%
0'
#1069
1#
#1070
0#
#1071
1#
#1072
0#
1%
1'
#1073
1#
#1074
0#
#1075
1#
#1076
0#
0%
0'
#1077
1#
#1078
0#
1%
1&
#1079
1#
#1080
0#
#1081
1#
#1082
0#
0%
1'
#1083
1#
#1084
0#
1%
0&
#1085
1#
#1086
0#
1&
0'
#1087
1#
#1088
0#
#1089
1#
#1090
0#
0%
1'
#1091
1#
#1092
0#
#1093
1#
#1094
0#
1%
0'
#1095
1#
#1096
0#
0&
1'
#1097
1#
#1098
0#
1&
0'
#1099
1#
#1100
0#
#1101
1#
#1102
0#
0%
0&
#1103
1#
#1104
0#
1&
1'
#1105
1#
#1106
0#
1%
0&
#1107
1#
#1108
0#
#1109
1#
#1110
0#
#1111
1#
#1112
0#
1&
0'
#1113
1#
#1114
0#
0&
1'
#1115
1#
#1116
0#
#1117
1#
#1118
0#
0%
0'
#1119
1#
#1120
0#
1%
1'
#1121
1#
#1122
0#
0%
0'
#1123
1#
#1124
0#
1%
1&
#1125
1#
#1126
0#
0&
1'
#1127
1#
#1128
0#
#1129
1#
#1130
0#
#1131
1#
#1132
0#
1&
0'
#1133
1#
#1134
0#
#1135
1#
#1136
0#
0%
0&
#1137
1#
#1138
0#
1%
1&
#1139
1#
#1140
0#
0%
1'
#1141
1#
#1142
0#
1%
0&
#1143
1#
#1144
0#
0%
1&
#1145
1#
#1146
0#
0&
0'
#1147
1#
#1148
0#
1%
1'
#1149
1#
#1150
0#
0%
1&
#1151
1#
#1152
0#
0&
0'
#1153
1#
#1154
0#
1%
1&
#1155
1#
#1156
0#
0&
1'
#1157
1#
#1158
0#
1&
0'
#1159
1#
#1160
0#
0%
1'
#1161
1#
#1162
0#
1%
0'
#1163
1#
#1164
0#
0%
0&
#1165
1#
#1166
0#
1%
1&
#1167
1#
#1168
0#
0%
0&
#1169
1#
#1170
0#
1&
1'
#1171
1#
#1172
0#
1%
0&
#1173
1#
#1174
0#
#1175
1#
#1176
0#
1&
0'
#1177
1#
#1178
0#
0%
0&
#1179
1#
#1180
0#
#1181
1#
#1182
0#
1%
1'
#1183
1#
#1184
0#
#1185
1#
#1186
0#
0%
0'
#1187
1#
#1188
0#
1&
1'
#1189
1#
#1190
0#
1%
0&
#1191
1#
#1192
0#
0%
1&
#1193
1#
#1194
0#
#1195
1#
#1196
0#
1%
0'
#1197
1#
#1198
0#
0%
0&
#1199
1#
#1200
0#
1%
1'
#1201
1#
#1202
0#
1&
0'
#1203
1#
#1204
0#
0%
0&
#1205
1#
#1206
0#
1%
1&
#1207
1#
#1208
0#
#1209
1#
#1210
0#
0%
1'
#1211
1#
#1212
0#
1%
0'
#1213
1#
#1214
0#
0%
0&
#1215
1#
#1216
0#
#1217
1#
#1218
0#
1%
1'
#1219
1#
#1220
0#
#1221
1#
#1222
0#
#1223
1#
#1224
0#
1&
0'
#1225
1#
#1226
0#
#1227
1#
#1228
0#
0%
1'
#1229
1#
#1230
0#
1%
0'
#1231
1#
#1232
0#
0&
1'
#1233
1#
#1234
0#
0%
0'
#1235
1#
#1236
0#
1&
1'
#1237
1#
#1238
0#
1%
0'
#1239
1#
#1240
0#
0%
1'
#1241
1#
#1242
0#
1%
0&
#1243
1#
#1244
0#
1&
0'
#1245
1#
#1246
0#
0%
1'
#1247
1#
#1248
0#
1%
0'
#1249
1#
#1250
0#
0&
1'
#1251
1#
#1252
0#
0%
0'
#1253
1#
#1254
0#
1&
1'
#1255
1#
#1256
0#
1%
0'
#1257
1#
#1258
0#
0%
1'
#1259
1#
#1260
0#
#1261
1#
#1262
0#
1%
0&
#1263
1#
#1264
0#
1&
0'
#1265
1#
#1266
0#
0%
1'
#1267
1#
#1268
0#
1%
0'
#1269
1#
#1270
0#
#1271
1#
#1272
0#
0&
1'
#1273
1#
#1274
0#
#1275
1#
#1276
0#
#1277
1#
#1278
0#
#1279
1#
#1280
0#
#1281
1#
#1282
0#
0%
1&
#1283
1#
#1284
0#
1%
0'
#1285
1#
#1286
0#
0&
1'
#1287
1#
#1288
0#
0%
1&
#1289
1#
#1290
0#
#1291
1#
#1292
0#
1%
0'
#1293
1#
#1294
0#
0&
1'
#1295
1#
#1296
0#
0%
1&
#1297
1#
#1298
0#
#1299
1#
#1300
0#
#1301
1#
#1302
0#
1%
0'
#1303
1#
#1304
0#
0&
1'
#1305
1#
#1306
0#
#1307
1#
#1308
0#
0%
0'
#1309
1#
#1310
0#
#1311
1#
#1312
0#
1%
1'
#1313
1#
#1314
0#
#1315
1#
#1316
0#
#1317
1#
#1318
0#
0%
0'
#1319
1#
#1320
0#
#1321
1#
#1322
0#
1%
1&
#1323
1#
#1324
0#
0&
1'
#1325
1#
#1326
0#
#1327
1#
#1328
0#
1&
0'
#1329
1#
#1330
0#
#1331
1#
#1332
0#
0%
0&
#1333
1#
#1334
0#
1%
1&
#1335
1#
#1336
0#
0&
1'
#1337
1#
#1338
0#
1&
0'
#1339
1#
#1340
0#
#1341
1#
#1342
0#
0&
1'
#1343
1#
#1344
0#
0%
1&
#1345
1#
#1346
0#
#1347
1#
#1348
0#
1%
0&
#1349
1#
#1350
0#
1&
0'
#1351
1#
#1352
0#
0&
1'
#1353
1#
#1354
0#
0%
0'
#1355
1#
#1356
0#
#1357
1#
#1358
0#
1&
1'
#1359
1#
#1360
0#
1%
0&
#1361
1#
#1362
0#
#1363
1#
#1364
0#
0%
0'
#1365
1#
#1366
0#
1%
1&
#1367
1#
#1368
0#
0%
1'
#1369
1#
#1370
0#
1%
0'
#1371
1#
#1372
0#
0%
0&
#1373
1#
#1374
0#
1%
1'
#1375
1#
#1376
0#
1&
0'
#1377
1#
#1378
0#
0%
1'
#1379
1#
#1380
0#
#1381
1#
#1382
0#
#1383
1#
#1384
0#
#1385
1#
#1386
0#
1%
0&
#1387
1#
#1388
0#
#1389
1#
#1390
0#
0%
0'
#1391
1#
#1392
0#
1&
1'
#1393
1#
#1394
0#
0&
0'
#1395
1#
#1396
0#
1%
1'
#1397
1#
#1398
0#
0%
1&
#1399
1#
#1400
0#
1%
0'
#1401
1#
#1402
0#
#1403
1#
#1404
0#
0&
1'
#1405
1#
#1406
0#
0%
1&
#1407
1#
#1408
0#
0&
0'
#1409
1#
#1410
0#
#1411
1#
#1412
0#
1%
1'
#1413
1#
#1414
0#
1&
0'
#1415
1#
#1416
0#
0&
1'
#1417
1#
#1418
0#
0%
0'
#1419
1#
#1420
0#
#1421
1#
#1422
0#
1%
1'
#1423
1#
#1424
0#
1&
0'
#1425
1#
#1426
0#
0&
1'
#1427
1#
#1428
0#
1&
0'
#1429
1#
#1430
0#
0&
1'
#1431
1#
#1432
0#
0%
0'
#1433
1#
#1434
0#
1&
1'
#1435
1#
#1436
0#
1%
0&
#1437
1#
#1438
0#
0%
1&
#1439
1#
#1440
0#
0&
0'
#1441
1#
#1442
0#
1%
1&
#1443
1#
#1444
0#
0&
1'
#1445
1#
#1446
0#
#1447
1#
#1448
0#
0%
1&
#1449
1#
#1450
0#
1%
0'
#1451
1#
#1452
0#
0&
1'
#1453
1#
#1454
0#
#1455
1#
#1456
0#
#1457
1#
#1458
0#
0%
1&
#1459
1#
#1460
0#
1%
0'
#1461
1#
#1462
0#
#1463
1#
#1464
0#
0%
1'
#1465
1#
#1466
0#
1%
0'
#1467
1#
#1468
0#
#1469
1#
#1470
0#
0%
1'
#1471
1#
#1472
0#
#1473
1#
#1474
0#
1%
0'
#1475
1#
#1476
0#
0&
1'
#1477
1#
#1478
0#
1&
0'
#1479
1#
#1480
0#
0&
1'
#1481
1#
#1482
0#
0%
0'
#1483
1#
#1484
0#
#1485
1#
#1486
0#
#1487
1#
#1488
0#
#1489
1#
#1490
0#
1%
1'
#1491
1#
#1492
0#
#1493
1#
#1494
0#
1&
0'
#1495
1#
#1496
0#
0%
0&
#1497
1#
#1498
0#
1&
1'
#1499
1#
#1500
0#
0&
0'
#1501
1#
#1502
0#
1%
1'
#1503
1#
#1504
0#
#1505
1#
#1506
0#
#1507
1#
#1508
0#
0%
0'
#1509
1#
#1510
0#
1&
1'
#1511
1#
#1512
0#
1%
0&
#1513
1#
#1514
0#
1&
0'
#1515
1#
#1516
0#
0%
1'
#1517
1#
#1518
0#
1%
0'
#1519
1#
#1520
0#
0&
1'
#1521
1#
#1522
0#
#1523
1#
#1524
0#
#1525
1#
#1526
0#
0%
1&
#1527
1#
#1528
0#
1%
0&
#1529
1#
#1530
0#
0%
1&
#1531
1#
#1532
0#
1%
0'
#1533
1#
#1534
0#
0&
1'
#1535
1#
#1536
0#
#1537
1#
#1538
0#
1&
0'
#1539
1#
#1540
0#
0%
1'
#1541
1#
#1542
0#
#1543
1#
#1544
0#
1%
0'
#1545
1#
#1546
0#
0&
1'
#1547
1#
#1548
0#
0%
0'
#1549
1#
#1550
0#
1%
1&
#1551
1#
#1552
0#
0&
1'
#1553
1#
#1554
0#
0%
0'
#1555
1#
#1556
0#
#1557
1#
#1558
0#
1%
1&
#1559
1#
#1560
0#
0%
1'
#1561
1#
#1562
0#
#1563
1#
#1564
0#
1%
0'
#1565
1#
#1566
0#
0%
0&
#1567
1#
#1568
0#
1%
1&
#1569
1#
#1570
0#
0%
0&
#1571
1#
#1572
0#
#1573
1#
#1574
0#
1%
1&
#1575
1#
#1576
0#
0%
0&
#1577
1#
#1578
0#
1%
1'
#1579
1#
#1580
0#
#1581
1#
#1582
0#
0%
0'
#1583
1#
#1584
0#
#1585
1#
#1586
0#
1&
1'
#1587
1#
#1588
0#
#1589
1#
#1590
0#
0&
0'
#1591
1#
#1592
0#
1&
1'
#1593
1#
#1594
0#
#1595
1#
#1596
0#
0&
0'
#1597
1#
#1598
0#
#1599
1#
#1600
0#
1%
1'
#1601
1#
#1602
0#
0%
1&
#1603
1#
#1604
0#
#1605
1#
#1606
0#
0&
0'
#1607
1#
#1608
0#
#1609
1#
#1610
0#
1%
1&
#1611
1#
#1612
0#
0%
1'
#1613
1#
#1614
0#
1%
0'
#1615
1#
#1616
0#
#1617
1#
#1618
0#
0%
1'
#1619
1#
#1620
0#
0&
0'
#1621
1#
#1622
0#
1%
1'
#1623
1#
#1624
0#
1&
0'
#1625
1#
#1626
0#
0%
0&
#1627
1#
#1628
0#
1%
1'
#1629
1#
#1630
0#
0%
0'
#1631
1#
#1632
0#
#1633
1#
#1634
0#
1%
1'
#1635
1#
#1636
0#
#1637
1#
#1638
0#
1&
0'
#1639
1#
#1640
0#
0%
0&
#1641
1#
#1642
0#
#1643
1#
#1644
0#
1%
1&
#1645
1#
#1646
0#
0&
1'
#1647
1#
#1648
0#
0%
1&
#1649
1#
#1650
0#
1%
0&
#1651
1#
#1652
0#
0%
0'
#1653
1#
#1654
0#
1%
1&
#1655
1#
#1656
0#
0%
1'
#1657
1#
#1658
0#
1%
0'
#1659
1#
#1660
0#
#1661
1#
#1662
0#
0%
1'
#1663
1#
#1664
0#
1%
0'
#1665
1#
#1666
0#
#1667
1#
#1668
0#
0&
1'
#1669
1#
#1670
0#
0%
1&
#1671
1#
#1672
0#
#1673
1#
#1674
0#
#1675
1#
#1676
0#
#1677
1#
#1678
0#
1%
0'
#1679
1#
#1680
0#
0&
1'
#1681
1#
#1682
0#
1&
0'
#1683
1#
